add_pinyin_key
