Metadata-Version: 2.1
Name: add-pinyin-key
Version: 0.0.2
Summary: Add pinyin keys to Chinese bib entries
Home-page: https://github.com/Yao1993/add-pinyin-key
Author: Yao Xu
Author-email: yaoxu@mail.ustc.edu.cn
License: MIT
Keywords: Bib
Platform: UNKNOWN
